odoo8_addon_hr_salary_rule_reference-8.0.1.0.0-py2.7-nspkg.pth
odoo_addons/hr_salary_rule_reference/__openerp__.py
odoo_addons/hr_salary_rule_reference/__init__.py
odoo_addons/hr_salary_rule_reference/README.rst
odoo_addons/hr_salary_rule_reference/models/__init__.py
odoo_addons/hr_salary_rule_reference/models/hr_salary_rule.py
odoo_addons/hr_salary_rule_reference/static/description/icon.png
odoo8_addon_hr_salary_rule_reference-8.0.1.0.0.dist-info/top_level.txt
odoo8_addon_hr_salary_rule_reference-8.0.1.0.0.dist-info/WHEEL
odoo8_addon_hr_salary_rule_reference-8.0.1.0.0.dist-info/RECORD
odoo8_addon_hr_salary_rule_reference-8.0.1.0.0.dist-info/metadata.json
odoo8_addon_hr_salary_rule_reference-8.0.1.0.0.dist-info/DESCRIPTION.rst
odoo8_addon_hr_salary_rule_reference-8.0.1.0.0.dist-info/METADATA
odoo8_addon_hr_salary_rule_reference-8.0.1.0.0.dist-info/namespace_packages.txt
