Metadata-Version: 2.0
Name: odoo8-addon-hr-salary-rule-reference
Version: 8.0.1.0.0
Summary: Salary Rule Reference
Home-page: https://www.savoirfairelinux.com
Author: UNKNOWN
Author-email: UNKNOWN
License: AGPL-3
Platform: UNKNOWN
Requires-Dist: odoo (<9.0a,>=8.0a)
Classifier: Programming Language :: Python :: 2.7
Classifier: Framework :: Odoo
Classifier: License :: OSI Approved :: GNU Affero General Public License v3
